{
  "12274": {"team_id": 12274, "team": "Argentina",     "coach": "Jorge Sampaoli"},
  "8493":  {"team_id": 8493,  "team": "Australia",     "coach": "Bert van Marwijk"},
  "5629":  {"team_id": 5629,  "team": "Belgium",       "coach": "Roberto Martínez"},
  "6380":  {"team_id": 6380,  "team": "Brazil",        "coach": "Tite"},
  "12430": {"team_id": 12430, "team": "Colombia",      "coach": "José Pékerman"},
  "16871": {"team_id": 16871, "team": "Costa Rica",    "coach": "Óscar Ramírez"},
  "9598":  {"team_id": 9598,  "team": "Croatia",       "coach": "Zlatko Dalić"},
  "7712":  {"team_id": 7712,  "team": "Denmark",       "coach": "Åge Hareide"},
  "16129": {"team_id": 16129, "team": "Egypt",         "coach": "Héctor Cúper"},
  "2413":  {"team_id": 2413,  "team": "England",       "coach": "Gareth Southgate"},
  "4418":  {"team_id": 4418,  "team": "France",        "coach": "Didier Deschamps"},
  "3148":  {"team_id": 3148,  "team": "Germany",       "coach": "Joachim Löw"},
  "7839":  {"team_id": 7839,  "team": "Iceland",       "coach": "Heimir Hallgrímsson"},
  "10840": {"team_id": 10840, "team": "Iran",          "coach": "Carlos Queiroz"},
  "12913": {"team_id": 12913, "team": "Japan",         "coach": "Akira Nishino"},
  "14855": {"team_id": 14855, "team": "Korea Republic","coach": "Shin Tae-yong"},
  "15473": {"team_id": 15473, "team": "Mexico",        "coach": "Juan Carlos Osorio"},
  "16216": {"team_id": 16216, "team": "Morocco",       "coach": "Hervé Renard"},
  "16823": {"team_id": 16823, "team": "Nigeria",       "coach": "Gernot Rohr"},
  "17929": {"team_id": 17929, "team": "Panama",        "coach": "Hernán Darío Gómez"},
  "15594": {"team_id": 15594, "team": "Peru",          "coach": "Ricardo Gareca"},
  "13869": {"team_id": 13869, "team": "Poland",        "coach": "Adam Nawałka"},
  "9905":  {"team_id": 9905,  "team": "Portugal",      "coach": "Fernando Santos"},
  "14358": {"team_id": 14358, "team": "Russia",        "coach": "Stanislav Cherchesov"},
  "16521": {"team_id": 16521, "team": "Saudi Arabia",  "coach": "Juan Antonio Pizzi"},
  "19314": {"team_id": 19314, "team": "Senegal",       "coach": "Aliou Cissé"},
  "17322": {"team_id": 17322, "team": "Serbia",        "coach": "Mladen Krstajić"},
  "1598":  {"team_id": 1598,  "team": "Spain",         "coach": "Fernando Hierro"},
  "7047":  {"team_id": 7047,  "team": "Sweden",        "coach": "Janne Andersson"},
  "6697":  {"team_id": 6697,  "team": "Switzerland",   "coach": "Vladimir Petković"},
  "16276": {"team_id": 16276, "team": "Tunisia",       "coach": "Nabil Maâloul"},
  "15670": {"team_id": 15670, "team": "Uruguay",       "coach": "Óscar Tabárez"}
}